twikit/__init__.py
twikit/bookmark.py
twikit/community.py
twikit/constants.py
twikit/errors.py
twikit/geo.py
twikit/group.py
twikit/list.py
twikit/media.py
twikit/message.py
twikit/notification.py
twikit/streaming.py
twikit/trend.py
twikit/tweet.py
twikit/user.py
twikit/utils.py
twikit/_captcha/__init__.py
twikit/_captcha/base.py
twikit/_captcha/capsolver.py
twikit/client/client.py
twikit/client/gql.py
twikit/client/v11.py
twikit/guest/__init__.py
twikit/guest/client.py
twikit/guest/tweet.py
twikit/guest/user.py
twikit/ui_metrics/__init__.py
twikit/ui_metrics/dom.py
twikit/x_client_transaction/__init__.py
twikit/x_client_transaction/cubic_curve.py
twikit/x_client_transaction/interpolate.py
twikit/x_client_transaction/rotation.py
twikit/x_client_transaction/transaction.py
twikit/x_client_transaction/utils.py
twikitfks-2.3.1.dist-info/licenses/LICENSE
twikitfks-2.3.1.dist-info/METADATA
twikitfks-2.3.1.dist-info/WHEEL
twikitfks-2.3.1.dist-info/top_level.txt
twikitfks-2.3.1.dist-info/RECORD
