Metadata-Version: 2.4
Name: twikitfks
Version: 2.3.1
Summary: Fork from twikit 2.3.1, conversation twitter spit
Home-page: https://github.com/d60/twikit
Requires-Python: >=3.8
License-File: LICENSE
Requires-Dist: beautifulsoup4>=4.13.4
Requires-Dist: build>=1.2.2.post1
Requires-Dist: filetype>=1.2.0
Requires-Dist: httpx[socks]>=0.28.1
Requires-Dist: js2py-3-13>=0.74.1
Requires-Dist: lxml>=5.4.0
Requires-Dist: m3u8>=6.0.0
Requires-Dist: pyotp>=2.9.0
Requires-Dist: webvtt-py>=0.5.1
Dynamic: home-page
Dynamic: license-file
Dynamic: requires-python
